ytcl/__init__.py
ytcl/common.py
ytcl/dostuff.py
ytcl/models.py
ytcl/tasks.py
ytcl/youtube_api.py
ytcl/statics/common.css
ytcl/statics/common.js
ytcl/statics/htmx.min.js
ytcl/statics/jquery.min.js
ytcl/statics/miniplayer.js
ytcl/statics/missing-thumbnail.jpg
ytcl/statics/scrollbydiv.js
ytcl/templates/AddChannel.html
ytcl/templates/BrowseChannel.html
ytcl/templates/Downloads.html
ytcl/templates/Index.html
ytcl/templates/ModifyIgnoreTerms.html
ytcl/templates/RecentlyPublished.html
ytcl/templates/Search.html
ytcl/templates/video.html
ytvip-0.0.13.dist-info/METADATA
ytvip-0.0.13.dist-info/WHEEL
ytvip-0.0.13.dist-info/entry_points.txt
ytvip-0.0.13.dist-info/top_level.txt
ytvip-0.0.13.dist-info/RECORD
